steemhd/__init__.py
steemhd/hdpath.py
steemhd/pyhd.py
steemhd/steem_to_hdwallet.py
steemhd/base58_utils/__init__.py
steemhd/base58_utils/algo.py
steemhd/base58_utils/base58_ex.py
steemhd/base58_utils/base58_steem.py
steemhd/base58_utils/base58_tron.py
steemhd/base58_utils/bech32.py
steemhd/base58_utils/bech32_base.py
steemhd/base58_utils/bech32_ex.py
steemhd/base58_utils/bytesutils.py
steemhd/base58_utils/cypto.py
steemhd/base58_utils/integer.py
steemhd/base58_utils/p2wpkh.py
steemhd-1.2.0.dist-info/METADATA
steemhd-1.2.0.dist-info/WHEEL
steemhd-1.2.0.dist-info/top_level.txt
steemhd-1.2.0.dist-info/RECORD
